{
  "country": "China",
  "country_code": "CN",
  "industry": "Communications Equipment",
  "industry_group": "Technology Hardware & Equipment",
  "kind": "stock",
  "listings": [
    {
      "currency": "CNY",
      "exchange_mic": "XSHE",
      "symbol": "002231.SZ"
    }
  ],
  "market_cap_band": "Small Cap",
  "name": "Allwin Telecommunication Co., Ltd.",
  "primary_symbol": "002231.SZ",
  "provenance": {
    "fetched_at": "2026-05-09T21:49:07Z",
    "license": "MIT",
    "source": "FinanceDatabase",
    "source_url": "https://github.com/JerBouma/FinanceDatabase"
  },
  "schema_version": "1.0.0",
  "sector": "Information Technology",
  "summary": "Allwin Telecommunication Co., Ltd. develops, produces, and sells radio frequency, microwave, and wireless communications network coverage system products in China and internationally. It offers repeater series products, including wireless wideband, wireless channel selective, fiber optic, and frequency shifting repeaters, as well as boosters, micro-cell boosters, base station extending systems, and bi-directional tower-mounted amplifiers. The company also provides microwave passive components, such as micro-strip and cavity power splitters, micro-strip and cavity power couplers, single-band and multi-band combiners, 3 dB hybrid couplers, attenuators, and load components. In addition, it offers antenna series products comprising indoor ceiling omni-directional, indoor panel directional, outdoor panel directional, outdoor yagi directional, grid parabolic, corner, outdoor directional, and special antennas. Further, the company provides network management monitor systems, repeater-supported network software systems, digital multimedia broadcasting gap fillers, and mini-repeaters. Additionally, it offers solutions for the coverage of scenic spots, sea areas, tunnels, roads and railways, suburban and rural areas, stadiums and exhibition centers, university campus, and residential districts, as well as for indoor coverage; and for the dispatch of wireless network resources, upgradation of 3G indoor coverage system, and elevators. Allwin Telecommunication Co., Ltd. was founded in 2000 and is headquartered in Shenyang, China.",
  "website": "http://www.syallwin.com"
}
