{
  "country": "Taiwan, Province of China",
  "country_code": "TW",
  "industry": "Distributors",
  "industry_group": "Retailing",
  "kind": "stock",
  "listings": [
    {
      "currency": "TWD",
      "exchange_mic": "XTAI",
      "symbol": "1323.TW"
    }
  ],
  "market_cap_band": "Micro Cap",
  "name": "Yonyu Plastics Co., Ltd.",
  "primary_symbol": "1323.TW",
  "provenance": {
    "fetched_at": "2026-05-09T21:49:07Z",
    "license": "MIT",
    "source": "FinanceDatabase",
    "source_url": "https://github.com/JerBouma/FinanceDatabase"
  },
  "schema_version": "1.0.0",
  "sector": "Consumer Discretionary",
  "summary": "Yonyu Plastics Co., Ltd. manufactures and sells plastic packaging products worldwide. The company offers home and personal cleaning, pharmaceutical, and green packaging products, as well as cosmetic package materials; and other products comprising cable accessories and other injection/extrusion products. It also provides color matching and master batch compounding, mold design and fabrication, plastic molding, cosmetic ingredient developing and filling, product design, computer-aided raw color recipe design, injection, blow molding, and tube manufacturing services; and various decoration services, such as printing, hot stamping, labeling, metallization, UV coating, and automated assembly services. The company was founded in 1964 and is based in Tainan City, Taiwan.",
  "website": "http://www.yonyu.com.tw"
}
