{
  "country": "Taiwan, Province of China",
  "country_code": "TW",
  "industry": "Electrical Equipment",
  "industry_group": "Capital Goods",
  "kind": "stock",
  "listings": [
    {
      "currency": "USD",
      "exchange_mic": "XNYS",
      "symbol": "3163.TWO"
    }
  ],
  "market_cap_band": "Micro Cap",
  "name": "Browave Corporation",
  "primary_symbol": "3163.TWO",
  "provenance": {
    "fetched_at": "2026-05-17T08:09:19Z",
    "license": "MIT",
    "source": "FinanceDatabase",
    "source_url": "https://github.com/JerBouma/FinanceDatabase"
  },
  "schema_version": "1.0.0",
  "sector": "Industrials",
  "summary": "Browave Corporation operates as an original equipment manufacturing/original design manufacturing development, production, and sales company in the optical fiber communication industry in Taiwan and internationally. Its products include compact coarse wavelength division multiplexers and demultiplexers; splitter modules; add/drop filters; amplifier components consisting of isolators and gain flattening filters; fused biconic taper WBC/WDM coupler and planar lightwave circuit splitters; fan-out cabling systems, adapters, and patchcords/pigtails; MPO/MTP cables; and fiber arrays, collimators, and pigtails. The company also provides optical devices and optical module products, such as isolators, couplers, DWDM, IPD, EDFA, ROSA, BOSA, etc. Its products are used in long haul communications network, metropolitan area network, central office fiber-to-the-home, and cloud data center applications. In addition, the company provides contract manufacturing services. Browave Corporation was founded in 1998 and is headquartered in Hsinchu City, Taiwan.",
  "website": "http://www.browave.com"
}
