{
  "country": "India",
  "country_code": "IN",
  "industry_group": "Consumer Services",
  "kind": "stock",
  "listings": [
    {
      "currency": "INR",
      "exchange_mic": "XBOM",
      "symbol": "AHLWEST.BO"
    }
  ],
  "market_cap_band": "Nano Cap",
  "name": "Asian Hotels (West) Limited",
  "primary_symbol": "AHLWEST.BO",
  "provenance": {
    "fetched_at": "2026-05-09T21:49:07Z",
    "license": "MIT",
    "source": "FinanceDatabase",
    "source_url": "https://github.com/JerBouma/FinanceDatabase"
  },
  "schema_version": "1.0.0",
  "sector": "Consumer Discretionary",
  "summary": "Asian Hotels (West) Limited is an Indian hospitality company that owns and operates hotels. The company's portfolio includes the Hyatt Regency Mumbai and the JW Marriott New Delhi Aerocity. Asian Hotels (West) Limited is based in Mumbai, India."
}
