{
  "country": "United States",
  "country_code": "US",
  "industry_group": "Banks",
  "kind": "stock",
  "listings": [
    {
      "currency": "USD",
      "exchange_mic": "XNYS",
      "symbol": "ASB^F"
    }
  ],
  "name": "Associated Banc-Corp Depositary Shares each representing a 1/40th interest in a share of Associated Banc-Corp 5.625% Non-Cumulative Perpetual Preferred Stock Series F",
  "primary_symbol": "ASB^F",
  "provenance": {
    "fetched_at": "2026-05-10T07:55:09Z",
    "license": "MIT",
    "source": "FinanceDatabase",
    "source_url": "https://github.com/JerBouma/FinanceDatabase"
  },
  "schema_version": "1.0.0",
  "sector": "Financials",
  "summary": "Associated Banc-Corp Depositary Shares represent fractional interests in preferred stock, specifically Series F. These shares offer a non-cumulative perpetual dividend. Associated Banc-Corp is headquartered in Green Bay, Wisconsin."
}
