{
  "country": "United States",
  "country_code": "US",
  "industry": "Software",
  "industry_group": "Software & Services",
  "kind": "stock",
  "listings": [
    {
      "currency": "USD",
      "exchange_mic": "XNYS",
      "symbol": "ASUR"
    }
  ],
  "market_cap_band": "Micro Cap",
  "name": "Asure Software, Inc.",
  "primary_symbol": "ASUR",
  "provenance": {
    "fetched_at": "2026-05-10T07:55:09Z",
    "license": "MIT",
    "source": "FinanceDatabase",
    "source_url": "https://github.com/JerBouma/FinanceDatabase"
  },
  "schema_version": "1.0.0",
  "sector": "Information Technology",
  "summary": "Asure Software, Inc. provides cloud-based human capital management solutions the United States. It helps various small and mid-sized businesses to develop human capital to get to the next level, stay compliant, and allocate resources toward growth. The company's solutions include Asure Payroll & Tax, an integrated cloud-based solution automates regulations associated with payroll and taxes, including wages, benefits, overtime, garnishments, tips, direct deposits, and fair labor standard act, as well as federal, state, and local payroll taxes; Asure HR, a cloud-based functionality that handles HR complexities, such as employee self-service that enable employees to access information, pay history, and company documents; and Asure Time & Attendance that provides cost savings and ROI gains come in the form of strategic use of labor dollars and the elimination of time theft. It also provides HR services that offers services ranging from an online compliance library and on-demand call center for various HR questions to outsourced HR function. Asure Software, Inc. was incorporated in 1985 and is headquartered in Austin, Texas.",
  "website": "http://www.asuresoftware.com"
}
