{
  "industry_group": "Materials",
  "kind": "stock",
  "listings": [
    {
      "currency": "USD",
      "exchange_mic": "XNYS",
      "symbol": "BASF.TI"
    }
  ],
  "name": "BASF",
  "primary_symbol": "BASF.TI",
  "provenance": {
    "fetched_at": "2026-05-17T08:09:19Z",
    "license": "MIT",
    "source": "FinanceDatabase",
    "source_url": "https://github.com/JerBouma/FinanceDatabase"
  },
  "schema_version": "1.0.0",
  "sector": "Materials",
  "summary": "BASF SE is a German multinational chemical company. It is the largest chemical producer in the world and creates chemicals for various industries including agriculture, construction and transportation, with headquarters in Ludwigshafen, Germany."
}
