{
  "country": "United Kingdom",
  "country_code": "GB",
  "industry": "Hotels, Restaurants & Leisure",
  "industry_group": "Consumer Services",
  "kind": "stock",
  "listings": [
    {
      "currency": "GBP",
      "exchange_mic": "XLON",
      "symbol": "BOWL.L"
    }
  ],
  "name": "Hollywood Bowl Group plc",
  "primary_symbol": "BOWL.L",
  "provenance": {
    "fetched_at": "2026-05-09T21:49:07Z",
    "license": "MIT",
    "source": "FinanceDatabase",
    "source_url": "https://github.com/JerBouma/FinanceDatabase"
  },
  "schema_version": "1.0.0",
  "sector": "Consumer Discretionary",
  "summary": "Hollywood Bowl Group plc operates ten-pin bowling centers. It operates a portfolio of 64 centers in the United Kingdom under the Hollywood Bowl, AMF, and Puttstars brands. Hollywood Bowl Group plc was incorporated in 2016 and is headquartered in Hemel Hempstead, the United Kingdom.",
  "website": "http://www.hollywoodbowlgroup.com"
}
