{
  "country": "United States",
  "country_code": "US",
  "industry": "Household Products",
  "industry_group": "Household & Personal Products",
  "kind": "stock",
  "listings": [
    {
      "currency": "USD",
      "exchange_mic": "XNYS",
      "symbol": "EDMCQ"
    }
  ],
  "market_cap_band": "Nano Cap",
  "name": "Education Management Corporation",
  "primary_symbol": "EDMCQ",
  "provenance": {
    "fetched_at": "2026-05-09T21:49:07Z",
    "license": "MIT",
    "source": "FinanceDatabase",
    "source_url": "https://github.com/JerBouma/FinanceDatabase"
  },
  "schema_version": "1.0.0",
  "sector": "Consumer Staples",
  "summary": "Education Management Corporation provides post-secondary education in North America. It offers academic programs to students through campus-based and online instruction to earn undergraduate and graduate degrees, and various specialized non-degree diplomas in a range of disciplines comprising business, culinary, design, education, fashion, health sciences, information technology, legal, media arts, and psychology and behavioral sciences. The company was founded in 1962 and is headquartered in Pittsburgh, Pennsylvania. On June 29, 2018, Education Management Corporation filed a voluntary petition for liquidation under Chapter 7 in the U.S. Bankruptcy Court for the District of Delaware. It is in joint administration with The Art Institute Of Philadelphia Limited Partnership.",
  "website": "http://www.edmc.edu"
}
