{
  "identifiers": {
    "composite_figi": "BBG000DNWW44",
    "isin": "EGS691A1C011"
  },
  "industry_group": "Diversified Financials",
  "isin": "EGS691A1C011",
  "kind": "stock",
  "listings": [
    {
      "currency": "EGP",
      "exchange_mic": "XCAI",
      "symbol": "EGS691A1C011.CA"
    }
  ],
  "name": "PRIME HOLDING",
  "primary_symbol": "EGS691A1C011.CA",
  "provenance": {
    "fetched_at": "2026-05-09T21:49:07Z",
    "license": "MIT",
    "source": "FinanceDatabase",
    "source_url": "https://github.com/JerBouma/FinanceDatabase"
  },
  "schema_version": "1.0.0",
  "sector": "Financials",
  "summary": "PRIME HOLDING is a financial services company that provides investment banking, brokerage, and asset management services. The company serves individual and institutional clients in the MENA region. The company is based in Egypt."
}
