{
  "country": "United States",
  "country_code": "US",
  "identifiers": {
    "isin": "GB0005603997"
  },
  "industry": "Capital Markets",
  "industry_group": "Diversified Financials",
  "isin": "GB0005603997",
  "kind": "stock",
  "listings": [
    {
      "currency": "USD",
      "exchange_mic": "XNYS",
      "symbol": "LGI"
    },
    {
      "currency": "USD",
      "exchange_mic": "XNYS",
      "symbol": "LGI.BE"
    },
    {
      "currency": "AED",
      "exchange_mic": "DIFX",
      "symbol": "LGI.DU"
    }
  ],
  "market_cap_band": "Nano Cap",
  "name": "Lazard Global Total Return and Income Fund, Inc.",
  "primary_symbol": "LGI",
  "provenance": {
    "fetched_at": "2026-05-09T21:49:07Z",
    "license": "MIT",
    "source": "FinanceDatabase",
    "source_url": "https://github.com/JerBouma/FinanceDatabase"
  },
  "schema_version": "1.0.0",
  "sector": "Financials",
  "summary": "Lazard Global Total Return and Income Fund, Inc. is a closed ended balanced mutual fund launched and managed by Lazard Asset Management LLC. It invests in public equity and fixed income markets across the globe. The fund primarily invests in stocks of companies with market capitalization over $5 billion. It makes its fixed income investments in short duration market forward currency contracts and other market debt instruments. The fund typically employs fundamental analysis with a bottom-up stock picking approach using its global equity strategy and emerging income strategy to create its portfolio. It considers factors like financial condition, cash flows, strong balance sheets, sustainability of returns, quality of management, competitive position, sensitivity to economic and market cycles, margin and sales trends, brand name strength, geographical breakdown, and macro environment for selecting individual securities. The fund benchmarks the performance of its portfolio against the MSCI World Index. Lazard Global Total Return and Income Fund, Inc. was formed on January 27, 2004 and is domiciled in the United States.",
  "website": "http://www.lazardnet.com/lam/us/closedfunds_lgi.shtml"
}
