{
  "country": "Switzerland",
  "country_code": "CH",
  "industry": "Insurance",
  "industry_group": "Insurance",
  "kind": "stock",
  "listings": [
    {
      "currency": "CHF",
      "exchange_mic": "XSWX",
      "symbol": "HELN.SW"
    }
  ],
  "market_cap_band": "Mid Cap",
  "name": "Helvetia Holding AG",
  "primary_symbol": "HELN.SW",
  "provenance": {
    "fetched_at": "2026-05-09T21:49:07Z",
    "license": "MIT",
    "source": "FinanceDatabase",
    "source_url": "https://github.com/JerBouma/FinanceDatabase"
  },
  "schema_version": "1.0.0",
  "sector": "Financials",
  "summary": "Helvetia Holding AG, through its subsidiaries, engages in life and non-life insurance, and reinsurance business in Switzerland, Germany, Austria, Spain, Italy, France, Liechtenstein, and internationally. It offers life insurance products in the areas of investment-linked, group life, and others; non-life insurance products in the areas of property, motor vehicle, health/accident, liability, and transport; and annuity insurance products and pension plans. The company was founded in 1858 and is headquartered in Sankt Gallen, Switzerland.",
  "website": "http://www.helvetia.com"
}
