{
  "country": "Australia",
  "country_code": "AU",
  "identifiers": {
    "isin": "JP3358000002"
  },
  "industry": "Specialty Retail",
  "industry_group": "Retailing",
  "isin": "JP3358000002",
  "kind": "stock",
  "listings": [
    {
      "currency": "AUD",
      "exchange_mic": "XASX",
      "symbol": "SHM.AX"
    }
  ],
  "market_cap_band": "Micro Cap",
  "name": "Shriro Holdings Limited",
  "primary_symbol": "SHM.AX",
  "provenance": {
    "fetched_at": "2026-05-09T21:49:07Z",
    "license": "MIT",
    "source": "FinanceDatabase",
    "source_url": "https://github.com/JerBouma/FinanceDatabase"
  },
  "schema_version": "1.0.0",
  "sector": "Consumer Discretionary",
  "summary": "Shriro Holdings Limited, together with its subsidiaries, manufactures and distributes kitchen appliances and consumer products in Australia and New Zealand. It operates through Kitchen Appliances and Consumer Products segments. The Kitchen Appliances segment offers ovens, cooktops, rangehoods, dishwashers, sinks, taps, ironing systems, and laundry tubs, as well as waste disposal and ducting solutions. The Consumer Products segment provides watches, calculators, electronic musical instruments, projectors, point of sale terminals, cameras, gas and charcoal barbeques, electric heaters, fans, air purifiers/dehumidifiers, and speakers, as well as fashion, car audio, professional DJ, amplifier, and Hi Fi products. The company also offers cash registers, and lighting and cooling products. In addition, it exports barbeques and accessories. The company markets and distributes its products under its own brands, including Omega, Robinhood, Everdure, and Omega Altise; and third party owned brands, such as Casio, Blanco, and Pioneer. Shriro Holdings Limited was incorporated in 2015 and is headquartered in Chatswood, Australia.",
  "website": "http://www.shriro.com.au"
}
