{
  "country": "Canada",
  "country_code": "CA",
  "industry": "Metals & Mining",
  "industry_group": "Materials",
  "kind": "stock",
  "listings": [
    {
      "currency": "EUR",
      "exchange_mic": "XSTU",
      "symbol": "KN6.SG"
    }
  ],
  "market_cap_band": "Nano Cap",
  "name": "KGL Resources Ltd.",
  "primary_symbol": "KN6.SG",
  "provenance": {
    "fetched_at": "2026-05-09T21:49:07Z",
    "license": "MIT",
    "source": "FinanceDatabase",
    "source_url": "https://github.com/JerBouma/FinanceDatabase"
  },
  "schema_version": "1.0.0",
  "sector": "Materials",
  "summary": "KGL Resources Ltd. engages in the acquisition, exploration, and evaluation of mineral resource properties in the Democratic Republic of Congo. It holds a 20% interest of mining rights in four iron ore concessions located in the Bamyan province of Afghanistan. The company was formerly known as Kilo Goldmines Ltd. and changed its name to KGL Resources Ltd. in March 2021. KGL Resources Ltd. is based in Toronto, Canada.",
  "website": "http://www.kilogoldmines.com"
}
