{
  "country": "China",
  "country_code": "CN",
  "identifiers": {
    "isin": "KYG5410P1000"
  },
  "industry": "Real Estate Management & Development",
  "industry_group": "Real Estate",
  "isin": "KYG5410P1000",
  "kind": "stock",
  "listings": [
    {
      "currency": "HKD",
      "exchange_mic": "XHKG",
      "symbol": "6999.HK"
    }
  ],
  "market_cap_band": "Small Cap",
  "name": "Leading Holdings Group Limited",
  "primary_symbol": "6999.HK",
  "provenance": {
    "fetched_at": "2026-05-17T08:09:19Z",
    "license": "MIT",
    "source": "FinanceDatabase",
    "source_url": "https://github.com/JerBouma/FinanceDatabase"
  },
  "schema_version": "1.0.0",
  "sector": "Real Estate",
  "summary": "Leading Holdings Group Limited engages in the development and sale of residential and commercial properties in China. The company operates through three segments: Property Development, Commercial Property Investment and Operation, and Hotel Operations. It also holds various commercial properties for further investment purpose; engages in hotel management business; and provides project management services. The company was formerly known as Leading China Holdings Limited. Leading Holdings Group Limited was founded in 1999 and is headquartered in Chengdu, China.",
  "website": "http://www.leading-group.com"
}
