{
  "country": "Japan",
  "country_code": "JP",
  "identifiers": {
    "isin": "KYG711391022"
  },
  "industry": "Construction & Engineering",
  "industry_group": "Capital Goods",
  "isin": "KYG711391022",
  "kind": "stock",
  "listings": [
    {
      "currency": "JPY",
      "exchange_mic": "XTKS",
      "symbol": "1833.T"
    }
  ],
  "market_cap_band": "Small Cap",
  "name": "Okumura Corporation",
  "primary_symbol": "1833.T",
  "provenance": {
    "fetched_at": "2026-05-09T21:49:07Z",
    "license": "MIT",
    "source": "FinanceDatabase",
    "source_url": "https://github.com/JerBouma/FinanceDatabase"
  },
  "schema_version": "1.0.0",
  "sector": "Industrials",
  "summary": "Okumura Corporation engages in the civil engineering, architectural construction, and investment development businesses in Japan. The company undertakes various civil engineering projects for railways, roads, power station facilities, sewage and water works, and others; and construction projects, including houses, public facilities, medical facilities, and office buildings. It also designs, manufactures, sells, and repairs construction/industrial machines and devices; and provides real estate, land, and building management services, as well as owns rental properties, such as residential buildings, warehouses, and land in Osaka and other areas; and manufactures and sells construction machinery, materials, and others. In addition, the company generates and sells renewable electricity. The company was founded in 1907 and is headquartered in Osaka, Japan.",
  "website": "http://www.okumuragumi.co.jp"
}
