{
  "country": "China",
  "country_code": "CN",
  "industry": "Real Estate Management & Development",
  "industry_group": "Real Estate",
  "kind": "stock",
  "listings": [
    {
      "currency": "USD",
      "exchange_mic": "XNYS",
      "symbol": "MDJH"
    }
  ],
  "market_cap_band": "Nano Cap",
  "name": "MDJM Ltd",
  "primary_symbol": "MDJH",
  "provenance": {
    "fetched_at": "2026-05-17T08:09:19Z",
    "license": "MIT",
    "source": "FinanceDatabase",
    "source_url": "https://github.com/JerBouma/FinanceDatabase"
  },
  "schema_version": "1.0.0",
  "sector": "Real Estate",
  "summary": "MDJM Ltd., through its subsidiaries and variable interest entity, operates as an integrated real estate services company in the People's Republic of China. It offers real estate agency services to real estate developers; and real estate consulting services, such as real estate marketing and planning, real estate agency services, and advertising planning services. The company also provides independent training and tourism development services. It serves real estate developers, real estate design institutes and agencies, urban planning bureaus of various levels of governments, and urban rail transportation companies, as well as urban infrastructure development companies. The company was formerly known as MDJLEAD LTD. and changed its name to MDJM Ltd. in May 2018. MDJM Ltd. was founded in 2002 and is headquartered in Tianjin, the People's Republic of China.",
  "website": "http://www.mdjhchina.com"
}
