{
  "country": "Indonesia",
  "country_code": "ID",
  "industry": "Communications Equipment",
  "industry_group": "Technology Hardware & Equipment",
  "kind": "stock",
  "listings": [
    {
      "currency": "IDR",
      "exchange_mic": "XIDX",
      "symbol": "MKNT.JK"
    }
  ],
  "market_cap_band": "Nano Cap",
  "name": "PT Mitra Komunikasi Nusantara Tbk",
  "primary_symbol": "MKNT.JK",
  "provenance": {
    "fetched_at": "2026-05-17T08:09:19Z",
    "license": "MIT",
    "source": "FinanceDatabase",
    "source_url": "https://github.com/JerBouma/FinanceDatabase"
  },
  "schema_version": "1.0.0",
  "sector": "Information Technology",
  "summary": "PT Mitra Komunikasi Nusantara Tbk distributes and sells telecommunication products in Indonesia. The company offers smartphones, tablets/pads, prepaid vouchers, SIM cards, and network products. It also sells its products online. The company was founded in 2008 and is headquartered in South Jakarta, Indonesia.",
  "website": "http://www.mknt.id"
}
