{
  "country": "Finland",
  "country_code": "FI",
  "industry": "Industrial Conglomerates",
  "industry_group": "Capital Goods",
  "kind": "stock",
  "listings": [
    {
      "currency": "USD",
      "exchange_mic": "XNYS",
      "symbol": "MXTOF"
    }
  ],
  "market_cap_band": "Mid Cap",
  "name": "Neles Oyj",
  "primary_symbol": "MXTOF",
  "provenance": {
    "fetched_at": "2026-05-17T08:09:19Z",
    "license": "MIT",
    "source": "FinanceDatabase",
    "source_url": "https://github.com/JerBouma/FinanceDatabase"
  },
  "schema_version": "1.0.0",
  "sector": "Industrials",
  "summary": "Neles Oyj provides flow control solutions and services worldwide. It offers control, on-off, emergency shutdown, butterfly, ball, globe, segment, and eccentric rotary plug valves; pneumatic, electric, and manual actuators; limit switches; and valve controllers, as well as valve parts. The company also provides valve repairs and maintenance, PID tuning and process control, and maintenance planning and lifecycle services. It offers its products to chemicals, energy, gas processing and LNG, industrial gas, marine, mining, metals and steel processing, pipeline, pulp, paper and bioproducts, refining, and water and wastewater industries. The company was formerly known as Metso Oyj. Neles Oyj was founded in 1956 and is headquartered in Vantaa, Finland.",
  "website": "http://www.neles.com"
}
