{
  "industry_group": "Capital Goods",
  "kind": "stock",
  "listings": [
    {
      "currency": "USD",
      "exchange_mic": "XNYS",
      "symbol": "NCGC.BE"
    }
  ],
  "name": "NCC A FRIA  SK 25",
  "primary_symbol": "NCGC.BE",
  "provenance": {
    "fetched_at": "2026-05-09T21:49:07Z",
    "license": "MIT",
    "source": "FinanceDatabase",
    "source_url": "https://github.com/JerBouma/FinanceDatabase"
  },
  "schema_version": "1.0.0",
  "sector": "Industrials",
  "summary": "NCC AB is a Swedish construction company engaged in building and infrastructure projects. The company operates in the Nordic region and provides construction services for residential, commercial, and industrial properties. NCC is headquartered in Solna, Sweden."
}
