{
  "country": "United States",
  "country_code": "US",
  "identifiers": {
    "composite_figi": "BBG00NRZYNK2",
    "figi": "BBG00NRZYNR5"
  },
  "industry": "Metals & Mining",
  "industry_group": "Materials",
  "kind": "stock",
  "listings": [
    {
      "currency": "CAD",
      "exchange_mic": "XCNQ",
      "symbol": "NSG.CN"
    }
  ],
  "market_cap_band": "Nano Cap",
  "name": "Star Gold Corp.",
  "primary_symbol": "NSG.CN",
  "provenance": {
    "fetched_at": "2026-05-09T21:49:07Z",
    "license": "MIT",
    "source": "FinanceDatabase",
    "source_url": "https://github.com/JerBouma/FinanceDatabase"
  },
  "schema_version": "1.0.0",
  "sector": "Materials",
  "summary": "Star Gold Corp., an exploration stage company, acquires, evaluates, and explores for precious and base metal properties in Canada. It primarily explores for gold, silver, and other base metal-bearing properties. The company's flagship property is the Longstreet Property, which includes 125 mineral claims covering an area of approximately 2,500 acres located in Nye County, Nevada. The company was formerly known as Elan Development, Inc. and changed its name to Star Gold Corp. in April 2008. Star Gold Corp. was founded in 2006 and is headquartered in Coeur d'Alene, Idaho.",
  "website": "http://www.stargoldcorp.com"
}
