{
  "country": "United States",
  "country_code": "US",
  "industry": "Banks",
  "industry_group": "Banks",
  "kind": "stock",
  "listings": [
    {
      "currency": "USD",
      "exchange_mic": "XNYS",
      "symbol": "OHPB"
    }
  ],
  "market_cap_band": "Nano Cap",
  "name": "Ohana Pacific Bank",
  "primary_symbol": "OHPB",
  "provenance": {
    "fetched_at": "2026-05-10T07:55:09Z",
    "license": "MIT",
    "source": "FinanceDatabase",
    "source_url": "https://github.com/JerBouma/FinanceDatabase"
  },
  "schema_version": "1.0.0",
  "sector": "Financials",
  "summary": "Ohana Pacific Bank provides personal and business banking products and services. It offers checking, savings, money market, and individual retirement accounts, as well as certificates of deposit. The company also provides residential mortgage loans, secured loans and lines of credit, home equity lines of credit, SBA loans, commercial term loans and lines of credit, commercial real estate loans and lines of credit, construction loans, and professional loans and lines of credit. In addition, it offers remote deposit capture, wire, and phone and online banking services, as well as safe deposit boxes. The company is based in Honolulu, Hawaii.",
  "website": "http://www.ohanapacificbank.com"
}
