{
  "industry_group": "Diversified Financials",
  "kind": "stock",
  "listings": [
    {
      "currency": "GBP",
      "exchange_mic": "XLON",
      "symbol": "OPP.L"
    }
  ],
  "market_cap_band": "Nano Cap",
  "name": "ORIGO PARTNERS PLC",
  "primary_symbol": "OPP.L",
  "provenance": {
    "fetched_at": "2026-05-17T08:09:19Z",
    "license": "MIT",
    "source": "FinanceDatabase",
    "source_url": "https://github.com/JerBouma/FinanceDatabase"
  },
  "schema_version": "1.0.0",
  "sector": "Financials",
  "summary": "Origo Partners PLC is an investment company focused on opportunities in the Asia Pacific region, particularly in private equity. The company invests in a range of sectors, including consumer, healthcare, and technology, with the aim of generating capital appreciation for its shareholders. Origo Partners is headquartered in London, United Kingdom."
}
