{
  "country": "United States",
  "country_code": "US",
  "industry_group": "Utilities",
  "kind": "stock",
  "listings": [
    {
      "currency": "USD",
      "exchange_mic": "XNYS",
      "symbol": "PCG-PE"
    }
  ],
  "market_cap_band": "Mid Cap",
  "name": "Pacific Gas and Electric Company",
  "primary_symbol": "PCG-PE",
  "provenance": {
    "fetched_at": "2026-05-10T07:55:09Z",
    "license": "MIT",
    "source": "FinanceDatabase",
    "source_url": "https://github.com/JerBouma/FinanceDatabase"
  },
  "schema_version": "1.0.0",
  "sector": "Utilities",
  "summary": "Pacific Gas and Electric Company generates, transmits, distributes, and sells electricity and natural gas to customers in northern and central California, the United States. It generates electricity using nuclear, hydroelectric, fossil fuel-fired, fuel cell, and photovoltaic sources. As of December 31, 2020, the company owns and operates approximately 18,000 circuit miles of interconnected transmission lines, 35 electric transmission substations, approximately 108,000 circuit miles of distribution lines, 68 transmission switching substations, and 758 distribution substations; and natural gas transmission, storage, and distribution system consisting of approximately 43,500 miles of distribution pipelines, approximately 6,300 miles of backbone and local transmission pipelines, and various storage facilities. It serves residential, commercial, industrial, and agricultural customers, as well as natural gas-fired electric generation facilities. The company was founded in 1905 and is headquartered in San Francisco, California. Pacific Gas and Electric Company is a subsidiary of PG&E Corporation.",
  "website": "http://www.pge.com"
}
