{
  "country": "Thailand",
  "country_code": "TH",
  "industry": "Industrial Conglomerates",
  "industry_group": "Capital Goods",
  "kind": "stock",
  "listings": [
    {
      "currency": "THB",
      "exchange_mic": "XBKK",
      "symbol": "TAPAC.BK"
    }
  ],
  "market_cap_band": "Micro Cap",
  "name": "Tapaco Public Company Limited",
  "primary_symbol": "TAPAC.BK",
  "provenance": {
    "fetched_at": "2026-05-10T07:55:09Z",
    "license": "MIT",
    "source": "FinanceDatabase",
    "source_url": "https://github.com/JerBouma/FinanceDatabase"
  },
  "schema_version": "1.0.0",
  "sector": "Industrials",
  "summary": "Tapaco Public Company Limited, together with its subsidiaries, manufactures and sells plastic and assembly parts for electrical and electronic products in Thailand, Sweden, and internationally. The company offers engineering plastic parts comprising semi-finished drive units, fax cover frames, fax bases, multi-function office equipment, and wireless handset bodies for fax machines; black-and-white and color photosensitive drums, laser printing machines, parts of laser printers, inkjet printers, mobile printers, etc. for printing and photocopying machines; tape driving and holding parts, CD grips, turn tables, etc. for car audio equipment; and other plastic parts that are used to manufacture household electrical appliances, such as refrigerators, air conditioners, auto parts, etc. It also manufactures plastic injection molds; and provides repair, maintenance, and modification services for plastic injection molds. In addition, the company is involved in the residential construction; investment, development, and sale of real estate properties; and cosmetic retailing business. Tapaco Public Company Limited was founded in 2000 and is headquartered in Chonburi, Thailand.",
  "website": "http://www.tapaco.com"
}
