{
  "country": "China",
  "country_code": "CN",
  "identifiers": {
    "cusip": "54951L109",
    "isin": "US54951L1098"
  },
  "industry": "Hotels, Restaurants & Leisure",
  "industry_group": "Consumer Services",
  "isin": "US54951L1098",
  "kind": "stock",
  "listings": [
    {
      "currency": "USD",
      "exchange_mic": "XNYS",
      "symbol": "0A6U.IL"
    },
    {
      "currency": "USD",
      "exchange_mic": "XNYS",
      "symbol": "LC0A.HA"
    },
    {
      "currency": "USD",
      "exchange_mic": "XNYS",
      "symbol": "LC0A.HM"
    },
    {
      "currency": "USD",
      "exchange_mic": "XNYS",
      "symbol": "LC0A.MU"
    },
    {
      "currency": "USD",
      "exchange_mic": "XNYS",
      "symbol": "LKNCY"
    },
    {
      "currency": "EUR",
      "exchange_mic": "XSTU",
      "symbol": "LC0A.SG"
    }
  ],
  "market_cap_band": "Small Cap",
  "name": "Luckin Coffee Inc.",
  "primary_symbol": "0A6U.IL",
  "provenance": {
    "fetched_at": "2026-05-10T07:55:09Z",
    "license": "MIT",
    "source": "FinanceDatabase",
    "source_url": "https://github.com/JerBouma/FinanceDatabase"
  },
  "schema_version": "1.0.0",
  "sector": "Consumer Discretionary",
  "summary": "Luckin Coffee Inc. engages in the retail sale of freshly brewed drinks, and pre-made food and beverage items in the People's Republic of China. It offers freshly brewed drinks, including freshly brewed coffee and non-coffee drinks; and food and beverage items, such as light meals. The company operates pick-up stores, relax stores, and delivery kitchens under the Luckin brand, as well as Luckin mobile app, Weixin mini-program, and other third-party platforms that cover the customer purchase process. As of March 31, 2019, it operated 2,370 stores, including 2,163 pick-up stores, 109 relax stores, and 98 delivery kitchens in 28 cities in the People's Republic of China. The company was founded in 2017 and is based in Xiamen, the People's Republic of China.",
  "website": "http://www.luckincoffee.com"
}
