{
  "country": "United States",
  "country_code": "US",
  "identifiers": {
    "composite_figi": "BBG000BR4ZK3",
    "cusip": "925550105",
    "figi": "BBG000BR53C2",
    "isin": "US9255501051"
  },
  "industry": "Communications Equipment",
  "industry_group": "Technology Hardware & Equipment",
  "isin": "US9255501051",
  "kind": "stock",
  "listings": [
    {
      "currency": "USD",
      "exchange_mic": "XNYS",
      "symbol": "UNS1.BE"
    },
    {
      "currency": "USD",
      "exchange_mic": "XNYS",
      "symbol": "UNS1.HA"
    },
    {
      "currency": "USD",
      "exchange_mic": "XNYS",
      "symbol": "UNS1.HM"
    },
    {
      "currency": "USD",
      "exchange_mic": "XNYS",
      "symbol": "UNS1.MU"
    },
    {
      "currency": "USD",
      "exchange_mic": "XNYS",
      "symbol": "VIAV"
    },
    {
      "currency": "EUR",
      "exchange_mic": "XETR",
      "symbol": "UNS1.DE"
    },
    {
      "currency": "AED",
      "exchange_mic": "DIFX",
      "symbol": "UNS1.DU"
    },
    {
      "currency": "EUR",
      "exchange_mic": "XFRA",
      "symbol": "UNS1.F"
    },
    {
      "currency": "EUR",
      "exchange_mic": "XSTU",
      "symbol": "UNS1.SG"
    },
    {
      "currency": "MXN",
      "exchange_mic": "XMEX",
      "symbol": "VIAV.MX"
    }
  ],
  "market_cap_band": "Mid Cap",
  "name": "VIAVI SOLUTIONS  DL-,001",
  "primary_symbol": "UNS1.BE",
  "provenance": {
    "fetched_at": "2026-05-17T08:09:19Z",
    "license": "MIT",
    "source": "FinanceDatabase",
    "source_url": "https://github.com/JerBouma/FinanceDatabase"
  },
  "schema_version": "1.0.0",
  "sector": "Information Technology",
  "summary": "VIAVI SOLUTIONS DL-,001 provides network and service enablement solutions to communications service providers and enterprises. Their offerings include network testing, monitoring, and assurance solutions. The company is headquartered in Scottsdale, Arizona.",
  "website": "http://www.viavisolutions.com"
}
