{
  "country": "Canada",
  "country_code": "CA",
  "industry": "Oil, Gas & Consumable Fuels",
  "industry_group": "Energy",
  "kind": "stock",
  "listings": [
    {
      "currency": "NOK",
      "exchange_mic": "XOSL",
      "symbol": "ZENA.OL"
    }
  ],
  "market_cap_band": "Nano Cap",
  "name": "Zenith Energy Ltd.",
  "primary_symbol": "ZENA.OL",
  "provenance": {
    "fetched_at": "2026-05-09T21:49:07Z",
    "license": "MIT",
    "source": "FinanceDatabase",
    "source_url": "https://github.com/JerBouma/FinanceDatabase"
  },
  "schema_version": "1.0.0",
  "sector": "Energy",
  "summary": "Zenith Energy Ltd., together with its subsidiaries, explores for and develops oil and natural gas in Italy, the Republic of the Congo, and internationally. It also produces and sells electricity and condensate. The company was formerly known as Canoel International Energy Ltd. and changed its name to Zenith Energy Ltd. in October 2014. Zenith Energy Ltd. was incorporated in 2007 and is based in Calgary, Canada.",
  "website": "http://www.zenithenergy.ca"
}
